MANIFEST.in
README.md
setup.py
s3deploy/__init__.py
s3deploy/core.py
s3deploy/s3.py
s3deploy.egg-info/PKG-INFO
s3deploy.egg-info/SOURCES.txt
s3deploy.egg-info/dependency_links.txt
s3deploy.egg-info/entry_points.txt
s3deploy.egg-info/requires.txt
s3deploy.egg-info/top_level.txt