Metadata-Version: 1.1
Name: s3deploy
Version: 0.0.1
Summary: The quickest way to deploy a static site to S3
Home-page: http://github.com/petermelias/s3-deploy
Author: Peter M. Elias
Author-email: petermelias@gmail.com
License: MIT
Platform: UNKNOWN
Classifier: Environment :: Web Environment
Classifier: Intended Audience :: Developers
Classifier: License :: OSI Approved :: MIT License
Classifier: Operating System :: OS Independent
Classifier: Programming Language :: Python
Classifier: Topic :: Internet :: WWW/HTTP :: Dynamic Content
Classifier: Topic :: Software Development :: Libraries :: Python Modules
